pocketbook/__init__.py
pocketbook/address_book.py
pocketbook/cli.py
pocketbook/constants.py
pocketbook/disclaimer.py
pocketbook/key_store.py
pocketbook/table.py
pocketbook/utils.py
pocketbook/commands/__init__.py
pocketbook/commands/add.py
pocketbook/commands/create.py
pocketbook/commands/delete.py
pocketbook/commands/list.py
pocketbook/commands/rename.py
pocketbook/commands/transfer.py
tests/commands/__init__.py
tests/commands/test_add.py
tests/commands/test_create.py
tests/commands/test_delete.py
tests/commands/test_list.py
tests/commands/test_rename.py
tests/commands/test_transfer.py
pocketbook-0.3.2.dist-info/LICENSE
pocketbook-0.3.2.dist-info/METADATA
pocketbook-0.3.2.dist-info/WHEEL
pocketbook-0.3.2.dist-info/entry_points.txt
pocketbook-0.3.2.dist-info/top_level.txt
pocketbook-0.3.2.dist-info/RECORD
