Metadata-Version: 2.1
Name: pocketbook
Version: 0.3.2
Summary: Command line wallet application for the Fetch.ai network
Home-page: https://github.com/fetchai/tools-pocketbook
Author: Edward FitzGerald
Author-email: edward.fitzgerald@fetch.ai
License: UNKNOWN
Project-URL: Bug Reports, https://github.com/fetchai/tools-pocketbook/issues
Project-URL: Source, https://github.com/fetchai/tools-pocketbook
Platform: UNKNOWN
Classifier: Development Status :: 4 - Beta
Classifier: Environment :: Console
Classifier: Intended Audience :: Developers
Classifier: License :: OSI Approved :: Apache Software License
Classifier: Programming Language :: Python :: 3
Classifier: Programming Language :: Python :: 3.5
Classifier: Programming Language :: Python :: 3.6
Classifier: Programming Language :: Python :: 3.7
Requires-Python: ~=3.5
Requires-Dist: fetchai-ledger-api (==1.0.1)
Requires-Dist: toml
Requires-Dist: colored
Provides-Extra: dev
Requires-Dist: check-manifest ; extra == 'dev'
Provides-Extra: test
Requires-Dist: coverage ; extra == 'test'
Requires-Dist: pytest ; extra == 'test'
Requires-Dist: flake8 ; extra == 'test'
